LICENSE
MANIFEST.in
setup.py
pymeta/__init__.py
pymeta/boot.py
pymeta/bootbase.py
pymeta/bootgenerator.py
pymeta/builder.py
pymeta/grammar.py
pymeta/runtime.py
pymeta/tests/__init__.py
pymeta/tests/test_builder.py
pymeta/tests/test_pymeta.py
pymeta/tests/test_runtime.py
pymeta2.egg-info/PKG-INFO
pymeta2.egg-info/SOURCES.txt
pymeta2.egg-info/dependency_links.txt
pymeta2.egg-info/top_level.txt