Metadata-Version: 1.0
Name: pymeta2
Version: 0.0.0
Summary: Parser generator
Home-page: http://www.allbuttonspressed.com/projects/pymeta2
Author: Waldemar Kornewald
Author-email: UNKNOWN
License: UNKNOWN
Platform: any
